yolov6/__init__.py
yolov6/main.py
yolov6-0.0.1.dist-info/DESCRIPTION.rst
yolov6-0.0.1.dist-info/METADATA
yolov6-0.0.1.dist-info/RECORD
yolov6-0.0.1.dist-info/WHEEL
yolov6-0.0.1.dist-info/metadata.json
yolov6-0.0.1.dist-info/top_level.txt
